ecsv/Cell.py
ecsv/Converter.py
ecsv/__init__.py
ecsv-0.0.6.dist-info/LICENSE
ecsv-0.0.6.dist-info/METADATA
ecsv-0.0.6.dist-info/WHEEL
ecsv-0.0.6.dist-info/top_level.txt
ecsv-0.0.6.dist-info/RECORD
