Metadata-Version: 2.1
Name: ecsv
Version: 0.0.6
Summary: An easy way to create HTML forms from CSV files
Author-email: Min Soo Kang <minsookang33@outlook.com>
Project-URL: Home, https://github.com/minnysoop/ecsv
Project-URL: Docs, https://github.com/minnysoop/ecsv/blob/main/README.md
Classifier: Programming Language :: Python :: 3
Classifier: License :: OSI Approved :: MIT License
Classifier: Operating System :: OS Independent
Requires-Python: >=3.10
License-File: LICENSE
